{
  "project_info": {
    "project_number": "12691391191",
    "firebase_url": "https://foody-5d79a.firebaseio.com",
    "project_id": "foody-5d79a",
    "storage_bucket": "foody-5d79a.appspot.com"
  },
  "client": [
    {
      "client_info": {
        "mobilesdk_app_id": "1:12691391191:android:8492e9cfce8bd4aa",
        "android_client_info": {
          "package_name": "com.example.hilary.foody"
        }
      },
      "oauth_client": [
        {
          "client_id": "12691391191-l9n429iks7bvuhmgec6j6b7hpfoll6u5.apps.googleusercontent.com",
          "client_type": 1,
          "android_info": {
            "package_name": "com.example.hilary.foody",
            "certificate_hash": "350aaf0f9185140068a657e1a74c2c71240df33b"
          }
        },
        {
          "client_id": "12691391191-1vmcn2hesk32cocqap0i92u8vkf38duh.apps.googleusercontent.com",
          "client_type": 3
        }
      ],
      "api_key": [
        {
          "current_key": "AIzaSyAhzbrbMD8PFr-d2nt7ImCFMJMyQoBEaxE"
        }
      ],
      "services": {
        "analytics_service": {
          "status": 1
        },
        "appinvite_service": {
          "status": 2,
          "other_platform_oauth_client": [
            {
              "client_id": "12691391191-1vmcn2hesk32cocqap0i92u8vkf38duh.apps.googleusercontent.com",
              "client_type": 3
            }
          ]
        },
        "ads_service": {
          "status": 2
        }
      }
    }
  ],
  "configuration_version": "1"
}